fds/__init__.py
fds/sdk/__init__.py
fds/sdk/EventsContribution/__init__.py
fds/sdk/EventsContribution/api_client.py
fds/sdk/EventsContribution/configuration.py
fds/sdk/EventsContribution/exceptions.py
fds/sdk/EventsContribution/model_utils.py
fds/sdk/EventsContribution/rest.py
fds/sdk/EventsContribution/api/__init__.py
fds/sdk/EventsContribution/api/events_contribution_api.py
fds/sdk/EventsContribution/apis/__init__.py
fds/sdk/EventsContribution/model/__init__.py
fds/sdk/EventsContribution/model/delete_response.py
fds/sdk/EventsContribution/model/delete_response_data.py
fds/sdk/EventsContribution/model/delete_response_data_event_data.py
fds/sdk/EventsContribution/model/delete_response_data_message.py
fds/sdk/EventsContribution/model/error_object.py
fds/sdk/EventsContribution/model/error_response.py
fds/sdk/EventsContribution/model/event_data.py
fds/sdk/EventsContribution/model/event_update_data.py
fds/sdk/EventsContribution/model/get_response.py
fds/sdk/EventsContribution/model/get_response_data.py
fds/sdk/EventsContribution/model/insert_request.py
fds/sdk/EventsContribution/model/insert_request_data.py
fds/sdk/EventsContribution/model/insert_response.py
fds/sdk/EventsContribution/model/insert_response_data.py
fds/sdk/EventsContribution/model/insert_response_data_event_data.py
fds/sdk/EventsContribution/model/insert_response_data_message.py
fds/sdk/EventsContribution/model/location_data.py
fds/sdk/EventsContribution/model/participants_data.py
fds/sdk/EventsContribution/model/registration_info_data.py
fds/sdk/EventsContribution/model/symbol_data.py
fds/sdk/EventsContribution/model/update_request.py
fds/sdk/EventsContribution/model/update_request_data.py
fds/sdk/EventsContribution/model/update_response.py
fds/sdk/EventsContribution/model/update_response_data.py
fds/sdk/EventsContribution/model/update_response_data_event_data.py
fds/sdk/EventsContribution/model/update_response_data_message.py
fds/sdk/EventsContribution/models/__init__.py
fds.sdk.EventsContribution-0.20.5.dist-info/LICENSE
fds.sdk.EventsContribution-0.20.5.dist-info/METADATA
fds.sdk.EventsContribution-0.20.5.dist-info/WHEEL
fds.sdk.EventsContribution-0.20.5.dist-info/top_level.txt
fds.sdk.EventsContribution-0.20.5.dist-info/RECORD
