Metadata-Version: 2.1
Name: fds.sdk.EventsContribution
Version: 0.20.5
Summary: Events Contribution client library for Python
Home-page: https://github.com/FactSet/enterprise-sdk/tree/main/code/python/EventsContribution/v0
Author: FactSet Research Systems
License: Apache License, Version 2.0
Keywords: FactSet,API,SDK
Platform: UNKNOWN
Requires-Python: >=3.7
License-File: LICENSE
Requires-Dist: urllib3 (>=1.25.3)
Requires-Dist: python-dateutil
Requires-Dist: fds.sdk.utils (>=1.0.0)
